twocaptcha/__init__.py
twocaptcha/api.py
twocaptcha/solver.py
2captcha_python-1.4.0.dist-info/LICENSE
2captcha_python-1.4.0.dist-info/METADATA
2captcha_python-1.4.0.dist-info/WHEEL
2captcha_python-1.4.0.dist-info/top_level.txt
2captcha_python-1.4.0.dist-info/RECORD
