Metadata-Version: 2.1
Name: 2captcha-python
Version: 1.4.0
Summary: Python module for easy integration with 2Captcha API
Home-page: https://github.com/2captcha/2captcha-python/
Author: 2Captcha
Author-email: info@2captcha.com
Keywords: 2captcha,captcha,api,captcha solver,reCAPTCHA,hCaptcha,FunCaptcha,Geetest,image captcha,Coordinates,Click Captcha,Geetest V4,Lemin captcha,Amazon WAF,Cloudflare Turnstile,Capy Puzzle,MTCaptcha,Friendly Captcha,Tencent,Cutcaptcha,DataDome,cybersiara
Classifier: Programming Language :: Python :: 3
Classifier: License :: OSI Approved :: MIT License
Classifier: Operating System :: OS Independent
Classifier: Topic :: Software Development :: Libraries :: Python Modules
Classifier: Topic :: Scientific/Engineering :: Image Recognition
Classifier: Topic :: Utilities
Classifier: Intended Audience :: Developers
Requires-Python: >=3.6
License-File: LICENSE
Requires-Dist: requests
